exact_cover_samples/__init__.py
exact_cover_samples/deco.py
exact_cover_samples/langford.py
exact_cover_samples/problems.py
exact_cover_samples/data/langford-10-solutions.csv
exact_cover_samples/data/langford-10.csv
exact_cover_samples/data/langford-11-solutions.csv
exact_cover_samples/data/langford-11.csv
exact_cover_samples/data/langford-3-solutions.csv
exact_cover_samples/data/langford-3.csv
exact_cover_samples/data/langford-4-solutions.csv
exact_cover_samples/data/langford-4.csv
exact_cover_samples/data/langford-5-solutions.csv
exact_cover_samples/data/langford-5.csv
exact_cover_samples/data/langford-6-solutions.csv
exact_cover_samples/data/langford-6.csv
exact_cover_samples/data/langford-7-solutions.csv
exact_cover_samples/data/langford-7.csv
exact_cover_samples/data/langford-8-solutions.csv
exact_cover_samples/data/langford-8.csv
exact_cover_samples/data/langford-9-solutions.csv
exact_cover_samples/data/langford-9.csv
exact_cover_samples/data/pentominos-2-5-6-solutions.csv
exact_cover_samples/data/pentominos-2-5-6.csv
exact_cover_samples/data/pentominos-3-20-solutions.csv
exact_cover_samples/data/pentominos-3-20.csv
exact_cover_samples/data/pentominos-4-15-solutions.csv
exact_cover_samples/data/pentominos-4-15.csv
exact_cover_samples/data/pentominos-5-12-solutions.csv
exact_cover_samples/data/pentominos-5-12.csv
exact_cover_samples/data/pentominos-6-10-solutions.csv
exact_cover_samples/data/pentominos-6-10.csv
exact_cover_samples/data/pentominos-8-8-solutions.csv
exact_cover_samples/data/pentominos-8-8.csv
exact_cover_samples/data/pentominos-8-9-solutions.csv
exact_cover_samples/data/pentominos-8-9.csv
exact_cover_samples/data/small-trimino.npy
exact_cover_samples/data/xcover-550-solutions.csv
exact_cover_samples/data/xcover-550.csv
exact_cover_samples/data/unwrap/cover_speed_test.py
exact_cover_samples-0.0.8.dist-info/METADATA
exact_cover_samples-0.0.8.dist-info/WHEEL
exact_cover_samples-0.0.8.dist-info/licenses/LICENSE
exact_cover_samples-0.0.8.dist-info/RECORD
